inmanta/__init__.py
inmanta/app.py
inmanta/command.py
inmanta/config.py
inmanta/const.py
inmanta/docstring_parser.py
inmanta/env.py
inmanta/exceptions.py
inmanta/export.py
inmanta/file_parser.py
inmanta/loader.py
inmanta/logging.py
inmanta/main.py
inmanta/model.py
inmanta/module.py
inmanta/moduletool.py
inmanta/mypy.py
inmanta/plugins.py
inmanta/profile_mem.py
inmanta/py.typed
inmanta/references.py
inmanta/reporter.py
inmanta/resources.py
inmanta/signals.py
inmanta/stable_api.py
inmanta/tornado.py
inmanta/tracing.py
inmanta/types.py
inmanta/user_setup.py
inmanta/validation_type.py
inmanta/warnings.py
inmanta/agent/__init__.py
inmanta/agent/_set_fork_server_process_name.py
inmanta/agent/agent.py
inmanta/agent/agent_new.py
inmanta/agent/cache.py
inmanta/agent/code_manager.py
inmanta/agent/config.py
inmanta/agent/executor.py
inmanta/agent/forking_executor.py
inmanta/agent/handler.py
inmanta/agent/in_process_executor.py
inmanta/agent/reporting.py
inmanta/agent/resourcepool.py
inmanta/agent/write_barier_executor.py
inmanta/ast/__init__.py
inmanta/ast/attribute.py
inmanta/ast/blocks.py
inmanta/ast/entity.py
inmanta/ast/export.py
inmanta/ast/type.py
inmanta/ast/variables.py
inmanta/ast/constraint/__init__.py
inmanta/ast/constraint/expression.py
inmanta/ast/statements/__init__.py
inmanta/ast/statements/assign.py
inmanta/ast/statements/call.py
inmanta/ast/statements/define.py
inmanta/ast/statements/generator.py
inmanta/compiler/__init__.py
inmanta/compiler/config.py
inmanta/compiler/data.py
inmanta/compiler/help/__init__.py
inmanta/compiler/help/explainer.py
inmanta/compiler/help/templates/index_collision.j2
inmanta/compiler/help/templates/modified_after_freeze.j2
inmanta/compiler/help/templates/module_v2_in_v1_path.j2
inmanta/data/__init__.py
inmanta/data/dataview.py
inmanta/data/model.py
inmanta/data/schema.py
inmanta/data/sqlalchemy.py
inmanta/db/__init__.py
inmanta/db/util.py
inmanta/db/versions/__init__.py
inmanta/db/versions/v1.py
inmanta/db/versions/v202211230.py
inmanta_core-18.0.0.dist-info/licenses/LICENSE
inmanta_core-18.0.0.dist-info/licenses/NOTICE
inmanta_core-18.0.0.dist-info/METADATA
inmanta_core-18.0.0.dist-info/WHEEL
inmanta_core-18.0.0.dist-info/entry_points.txt
inmanta_core-18.0.0.dist-info/top_level.txt
inmanta_core-18.0.0.dist-info/RECORD
