Metadata-Version: 2.4
Name: inmanta-core
Version: 18.0.0
Summary: Inmanta deployment tool
Home-page: https://github.com/inmanta/inmanta-core
Author: Inmanta
Author-email: code@inmanta.com
License: Apache Software License 2
Project-URL: Bug Tracker, https://github.com/inmanta/inmanta-core/issues
Project-URL: Documentation, https://docs.inmanta.com/community/latest/
Keywords: orchestrator orchestration configurationmanagement
Classifier: Development Status :: 5 - Production/Stable
Classifier: Intended Audience :: System Administrators
Classifier: Intended Audience :: Telecommunications Industry
Classifier: Operating System :: POSIX :: Linux
Classifier: Topic :: System :: Systems Administration
Classifier: Topic :: Utilities
Classifier: Programming Language :: Python :: 3.12
Requires-Python: >=3.12
License-File: LICENSE
License-File: NOTICE
Requires-Dist: asyncpg~=0.25
Requires-Dist: build~=1.0
Requires-Dist: click-plugins~=1.0
Requires-Dist: click<8.4,>=8.0
Requires-Dist: colorlog~=6.4
Requires-Dist: cookiecutter<3,>=1
Requires-Dist: crontab<2.0,>=0.23
Requires-Dist: cryptography<47,>=36
Requires-Dist: docstring-parser<0.18,>=0.10
Requires-Dist: email-validator<3,>=1
Requires-Dist: jinja2~=3.0
Requires-Dist: more-itertools<11,>=8
Requires-Dist: packaging<26.1,>=21.3
Requires-Dist: pip>=21.3
Requires-Dist: ply~=3.0
Requires-Dist: pydantic!=2.9.2,~=2.5
Requires-Dist: PyJWT~=2.0
Requires-Dist: pynacl~=1.5
Requires-Dist: python-dateutil~=2.0
Requires-Dist: pyyaml~=6.0
Requires-Dist: setuptools
Requires-Dist: texttable~=1.0
Requires-Dist: tornado>6.5
Requires-Dist: typing_inspect~=0.9
Requires-Dist: ruamel.yaml~=0.17
Requires-Dist: toml~=0.10
Requires-Dist: setproctitle~=1.3
Requires-Dist: SQLAlchemy~=2.0
Requires-Dist: strawberry-sqlalchemy-mapper==0.8.0
Requires-Dist: jsonpath-ng~=1.7
Provides-Extra: dev
Requires-Dist: inmanta-core[datatrace,debug,tracing]; extra == "dev"
Requires-Dist: inmanta-dev-dependencies[async,core,pytest]; extra == "dev"
Requires-Dist: inmanta-module-std; extra == "dev"
Requires-Dist: bumpversion; extra == "dev"
Requires-Dist: openapi_spec_validator; extra == "dev"
Requires-Dist: pep8-naming; extra == "dev"
Requires-Dist: pip2pi; extra == "dev"
Requires-Dist: psutil; extra == "dev"
Requires-Dist: time-machine; extra == "dev"
Requires-Dist: types-python-dateutil; extra == "dev"
Requires-Dist: types-PyYAML; extra == "dev"
Requires-Dist: types-setuptools; extra == "dev"
Requires-Dist: types-toml; extra == "dev"
Requires-Dist: furo; extra == "dev"
Requires-Dist: inmanta-sphinx; extra == "dev"
Requires-Dist: myst-parser; extra == "dev"
Requires-Dist: sphinx; extra == "dev"
Requires-Dist: sphinx-argparse; extra == "dev"
Requires-Dist: sphinx-autodoc-annotation; extra == "dev"
Requires-Dist: sphinx-click; extra == "dev"
Requires-Dist: sphinxcontrib-contentui; extra == "dev"
Requires-Dist: sphinxcontrib.datatemplates; extra == "dev"
Requires-Dist: sphinxcontrib-redoc; extra == "dev"
Requires-Dist: sphinxcontrib-serializinghtml; extra == "dev"
Requires-Dist: sphinx-design; extra == "dev"
Requires-Dist: Sphinx-Substitution-Extensions; extra == "dev"
Provides-Extra: debug
Requires-Dist: rpdb; extra == "debug"
Provides-Extra: pytest-inmanta-extensions
Requires-Dist: pytest-inmanta-extensions~=18.0.0.0.dev; extra == "pytest-inmanta-extensions"
Provides-Extra: datatrace
Requires-Dist: graphviz; extra == "datatrace"
Provides-Extra: tracing
Requires-Dist: logfire<5.0,>=0.46; extra == "tracing"
Requires-Dist: opentelemetry-instrumentation-asyncpg~=0.46b0; extra == "tracing"
Dynamic: author
Dynamic: author-email
Dynamic: classifier
Dynamic: description
Dynamic: description-content-type
Dynamic: home-page
Dynamic: keywords
Dynamic: license
Dynamic: license-file
Dynamic: project-url
Dynamic: provides-extra
Dynamic: requires-dist
Dynamic: requires-python
Dynamic: summary
